binarymeshformat/__init__.py
binarymeshformat/meshdata.py
binarymeshformat/reader.py
binarymeshformat/writer.py
binarymeshformat-1.0.dist-info/LICENSE
binarymeshformat-1.0.dist-info/METADATA
binarymeshformat-1.0.dist-info/WHEEL
binarymeshformat-1.0.dist-info/top_level.txt
binarymeshformat-1.0.dist-info/RECORD
