Metadata-Version: 2.1
Name: binarymeshformat
Version: 1.0
Summary: Reading and writing triangulated meshes
Home-page: https://github.com/PaluchLabUCL/DeformingMesh3D-plugin/tree/master/src/python
Author: Matthew Smith
Author-email: matthew.smith3@crick.ac.uk
License: UNKNOWN
Project-URL: Bug Tracker, https://github.com/PaluchLabUCL/DeformingMesh3D-plugin/issues
Platform: UNKNOWN
Classifier: Programming Language :: Python :: 3
Classifier: License :: OSI Approved :: MIT License
Classifier: Operating System :: OS Independent
Requires-Python: >=3.6
License-File: LICENSE
